{
  "parent": "hydrogenmod:recipes/root",
  "rewards": {
    "recipes": [
      "hydrogenmod:hydrogen_shovel"
    ]
  },
  "criteria": {
    "has_hydrogen": {
      "trigger": "minecraft:inventory_changed",
      "conditions": {
        "items": [
          {
            "item": "hydrogenmod:hydrogen"
          }
        ]
      }
    },
    "has_the_recipe": {
      "trigger": "minecraft:recipe_unlocked",
      "conditions": {
        "recipe": "hydrogenmod:hydrogen_shovel"
      }
    }
  },
  "requirements": [
    [
      "has_hydrogen",
      "has_the_recipe"
    ]
  ]
}
